ChannelAttribution.cp37-win_amd64.pyd
cypack/__init__.py
cypack/functions.h
cypack/generate_doc.py
cypack/main.py
cypack/data/Data.csv
ChannelAttribution-2.0.5.dist-info/LICENSE.txt
ChannelAttribution-2.0.5.dist-info/METADATA
ChannelAttribution-2.0.5.dist-info/WHEEL
ChannelAttribution-2.0.5.dist-info/top_level.txt
ChannelAttribution-2.0.5.dist-info/RECORD
