Metadata-Version: 2.1
Name: ChannelAttribution
Version: 2.0.5
Summary: Markov Model for Online Multi-Channel Attribution
Home-page: http://www.channelattribution.net
Author: Davide Altomare, David Loris
Author-email: info@channelattribution.net
License: GPLv3
Project-URL: Documentation, http://www.channelattribution.net
Project-URL: Code, https://gitlab.com/session-tech/ChannelAttribution
Project-URL: Issue tracker, https://gitlab.com/session-tech/ChannelAttribution/issues
Platform: UNKNOWN
Classifier: Development Status :: 5 - Production/Stable
Classifier: License :: OSI Approved :: GNU General Public License v3 (GPLv3)
Classifier: Intended Audience :: Education
Classifier: Intended Audience :: Science/Research
Classifier: Topic :: Scientific/Engineering
Classifier: Topic :: Scientific/Engineering :: Mathematics
Classifier: Natural Language :: English
Classifier: Operating System :: OS Independent
Classifier: Programming Language :: C++
Classifier: Programming Language :: Cython
Classifier: Programming Language :: Python
Classifier: Programming Language :: Python :: 3
Classifier: Programming Language :: Python :: 3.4
Classifier: Programming Language :: Python :: 3.5
Classifier: Programming Language :: Python :: 3.6
Classifier: Programming Language :: Python :: 3.7
Classifier: Programming Language :: Python :: 3 :: Only
Classifier: Programming Language :: Python :: Implementation :: CPython
Requires-Python: >=3.4
Requires-Dist: numpy
Requires-Dist: pandas
